{
  "strategy_id": "4a7a1a31-e209-4b23-891a-3899fb8e4c28",
  "backtest_date": "2024-10-07",
  "positions": [
    {
      "position_id": "entry-4-pos1",
      "entry_node_id": "entry-4",
      "entry_time": "2024-10-07T09:19:00",
      "entry_timestamp": "09:19:00",
      "instrument": "NIFTY",
      "symbol": "NIFTY:2024-10-10:OPT:25100:PE",
      "strike": "25100",
      "option_type": "PE",
      "expiry": "2024-10-10",
      "entry_price": 149.85,
      "quantity": 1,
      "lot_size": 1,
      "lots": 1.0,
      "side": "buy",
      "order_type": "MARKET",
      "order_id": "ENTRY_entry-4_20251130_084432",
      "re_entry_num": 0,
      "nifty_spot_at_entry": 0,
      "exchange": "NFO",
      "product_type": "intraday",
      "status": "CLOSED",
      "exit_node_id": "square-off-1",
      "exit_time": "N/A",
      "exit_timestamp": "N/A",
      "exit_price": 318.1,
      "exit_reason": "square_off",
      "duration_seconds": 0,
      "duration_minutes": 0,
      "pnl": 168.25,
      "pnl_percentage": 112.28
    },
    {
      "position_id": "entry-3-pos1",
      "entry_node_id": "entry-3",
      "entry_time": "2024-10-07T09:21:08",
      "entry_timestamp": "09:21:08",
      "instrument": "NIFTY",
      "symbol": "NIFTY:2024-10-10:OPT:25100:CE",
      "strike": "25100",
      "option_type": "CE",
      "expiry": "2024-10-10",
      "entry_price": 181.55,
      "quantity": 1,
      "lot_size": 1,
      "lots": 1.0,
      "side": "buy",
      "order_type": "MARKET",
      "order_id": "ENTRY_entry-3_20251130_084432",
      "re_entry_num": 0,
      "nifty_spot_at_entry": 0,
      "exchange": "NFO",
      "product_type": "intraday",
      "status": "CLOSED",
      "exit_node_id": "exit-3",
      "exit_time": "2024-10-07T09:26:42",
      "exit_timestamp": "09:26:42",
      "exit_price": 179.0,
      "exit_reason": "exit_condition_met",
      "duration_seconds": 334.0,
      "duration_minutes": 5.566666666666666,
      "pnl": -2.55,
      "pnl_percentage": -1.4
    },
    {
      "position_id": "entry-3-pos1",
      "entry_node_id": "entry-3",
      "entry_time": "2024-10-07T09:28:47",
      "entry_timestamp": "09:28:47",
      "instrument": "NIFTY",
      "symbol": "NIFTY:2024-10-10:OPT:25100:CE",
      "strike": "25100",
      "option_type": "CE",
      "expiry": "2024-10-10",
      "entry_price": 184.35,
      "quantity": 1,
      "lot_size": 1,
      "lots": 1.0,
      "side": "buy",
      "order_type": "MARKET",
      "order_id": "ENTRY_entry-3_20251130_084432",
      "re_entry_num": 1,
      "nifty_spot_at_entry": 0,
      "exchange": "NFO",
      "product_type": "intraday",
      "status": "CLOSED",
      "exit_node_id": "exit-3",
      "exit_time": "2024-10-07T09:29:36",
      "exit_timestamp": "09:29:36",
      "exit_price": 180.05,
      "exit_reason": "exit_condition_met",
      "duration_seconds": 49.0,
      "duration_minutes": 0.8166666666666667,
      "pnl": -4.3,
      "pnl_percentage": -2.33
    }
  ],
  "summary": {
    "total_positions": 3,
    "closed_positions": 3,
    "open_positions": 0,
    "total_pnl": 161.4,
    "winning_trades": 1,
    "losing_trades": 2,
    "breakeven_trades": 0,
    "win_rate": 33.33,
    "avg_win": 168.25,
    "avg_loss": -3.42,
    "avg_duration_minutes": 2.13,
    "largest_win": 168.25,
    "largest_loss": -4.3,
    "re_entries": 1
  }
}